README.rst
setup.py
twisted/plugins/txexiftool.py
txExiftool.egg-info/PKG-INFO
txExiftool.egg-info/SOURCES.txt
txExiftool.egg-info/dependency_links.txt
txExiftool.egg-info/not-zip-safe
txExiftool.egg-info/requires.txt
txExiftool.egg-info/top_level.txt
txexiftool/__init__.py
txexiftool/compat.py