Metadata-Version: 1.1
Name: txExiftool
Version: 0.1.3
Summary: Exiftool protocol and stream endpoint plugin to be used with Twisted
Home-page: https://github.com/znerol/txexiftool
Author: Lorenz Schori
Author-email: lo@znerol.ch
License: UNKNOWN
Platform: UNKNOWN
Classifier: Development Status :: 5 - Production/Stable
Classifier: Environment :: Plugins
Classifier: Framework :: Twisted
Classifier: Intended Audience :: Developers
Classifier: Intended Audience :: Information Technology
Classifier: License :: OSI Approved :: MIT License
Classifier: Operating System :: OS Independent
Classifier: Programming Language :: Python :: 2.7
Classifier: Programming Language :: Python :: 3.2
Classifier: Programming Language :: Python :: 3.3
Classifier: Programming Language :: Python :: 3.4
Classifier: Topic :: Multimedia :: Graphics :: Capture
